Metadata-Version: 2.1
Name: snrandymylib
Version: 0.1.0
Summary: A very basic calculator library
Home-page: UNKNOWN
Author: snrandy
Author-email: nfonandrew73@gmail.com
License: MIT
Keywords: calculator
Platform: UNKNOWN
License-File: LICENCE.txt
